mtmqujing/__init__.py
mtmqujing/convert.py
mtmqujing/exceptions.py
mtmqujing/qujing.py
mtmqujing-0.2.2.dist-info/licenses/LICENSE
mtmqujing-0.2.2.dist-info/METADATA
mtmqujing-0.2.2.dist-info/WHEEL
mtmqujing-0.2.2.dist-info/top_level.txt
mtmqujing-0.2.2.dist-info/RECORD
